[
    {
        "id": 1,
        "name": "Tour montañas rocosas",
        "price": 4000,
        "description": "Aqui va una descripcion del tour ofecido, con su duracion, lugar, requisitos y beneficios.",
        "image": "tour-alternativo-3-.jpg",
        "continente": "",
        "promedio": "",
        "opiniones": "",
        "pais": ""


    },
    {
        "id": 2,
        "name": "Tour montañas rocosas",
        "price": 4000,
        "description": "Aqui va una descripcion del tour ofecido, con su duracion, lugar, requisitos y beneficios.",
        "image": "tour-alternativo-3-.jpg",
        "continente": "",
        "promedio": "",
        "opiniones": "",
        "pais": ""
    },
    {
        "id": 3,
        "name": "Tour montañas rocosas",
        "price": 4000,
        "description": "Aqui va una descripcion del tour ofecido, con su duracion, lugar, requisitos y beneficios.",
        "image": "tour-alternativo-3-.jpg",
        "continente": "",
        "promedio": "",
        "opiniones": "",
        "pais": ""
    },
    {
        "id": 4,
        "name": "Tour montañas rocosas",
        "price": 4000,
        "description": "Aqui va una descripcion del tour ofecido, con su duracion, lugar, requisitos y beneficios.",
        "image": "tour-alternativo-3-.jpg",
        "continente": "",
        "promedio": "",
        "opiniones": "",
        "pais": ""
    },
    {
        "id": 5,
        "name": "Nikon Reflex D3500 - Kit",
        "description": "Incluye la cámara D3500, el objetivo zoom AF-P DX NIKKOR 18-55mm y el superteleobjetivo zoom compacto AF-P DX NIKKOR 70-300mm. Ambos objetivos enfocan de forma rápida y silenciosa, lo que resulta ideal para grabar metraje de vídeo sin que se escuche apenas el ruido del accionamiento.",
        "price": 53000,
        "discount": 20,
        "image": "img-camara-nikon.jpg",
        "category": "in-sale"
    },
    {
        "id": 6,
        "name": "Tour montañas rocosas",
        "price": 4000,
        "description": "Aqui va una descripcion del tour ofecido, con su duracion, lugar, requisitos y beneficios.",
        "image": "tour-alternativo-3-.jpg",
        "continente": "",
        "promedio": "",
        "opiniones": "",
        "pais": ""
    },
    {
        "id": 7,
        "name": "Tour montañas rocosas",
        "price": 4000,
        "description": "Aqui va una descripcion del tour ofecido, con su duracion, lugar, requisitos y beneficios.",
        "image": "tour-alternativo-3-.jpg",
        "continente": "",
        "promedio": "",
        "opiniones": "",
        "pais": ""
    },
    {
        "id": 8,
        "name": "Tour montañas rocosas",
        "price": 4000,
        "description": "Aqui va una descripcion del tour ofecido, con su duracion, lugar, requisitos y beneficios.",
        "image": "tour-alternativo-3-.jpg",
        "continente": "",
        "promedio": "",
        "opiniones": "",
        "pais": ""
    }
   
]
